misa/__init__.py
misa/admin.py
misa/apps.py
misa/filter.py
misa/forms.py
misa/models.py
misa/sitetrees.py
misa/tables.py
misa/tasks.py
misa/test_settings.py
misa/urls.py
misa/validators.py
misa/views.py
misa/migrations/0001_initial.py
misa/migrations/0002_IMPORT_DATA.py
misa/migrations/__init__.py
misa/migrations/backup/0002_IMPORT_DATA.py
misa/migrations/backup/__init__.py
misa/templates/base.html
misa/templates/template_structure.txt
misa/templates/gfiles/index.html
misa/templates/misa/addontologyterm_form.html
misa/templates/misa/assay_details.html
misa/templates/misa/assay_files.html
misa/templates/misa/assay_form.html
misa/templates/misa/chromatography_protocol_list.html
misa/templates/misa/chromatography_type_list.html
misa/templates/misa/chromatographyprotocol_form.html
misa/templates/misa/chromatographytype_form.html
misa/templates/misa/confirm_delete.html
misa/templates/misa/data_transformation_protocol_list.html
misa/templates/misa/datatransformationprotocol_form.html
misa/templates/misa/extraction_protocol_list.html
misa/templates/misa/extraction_type_list.html
misa/templates/misa/extractionprotocol_form.html
misa/templates/misa/extractiontype_form.html
misa/templates/misa/investigation_detail.html
misa/templates/misa/investigation_detail_tables.html
misa/templates/misa/investigation_form.html
misa/templates/misa/investigation_list.html
misa/templates/misa/isa_file_select.html
misa/templates/misa/measurement_protocol_list.html
misa/templates/misa/measurement_technique_list.html
misa/templates/misa/measurementprotocol_form.html
misa/templates/misa/measurementtechnique_form.html
misa/templates/misa/ontology_search_results.html
misa/templates/misa/ontologyterm_form.html
misa/templates/misa/ontologyterm_list.html
misa/templates/misa/organism_form.html
misa/templates/misa/organism_list.html
misa/templates/misa/organism_part_list.html
misa/templates/misa/organismpart_form.html
misa/templates/misa/sample_collection_protocol_list.html
django_misa-0.0.2.dist-info/LICENSE
django_misa-0.0.2.dist-info/METADATA
django_misa-0.0.2.dist-info/WHEEL
django_misa-0.0.2.dist-info/top_level.txt
django_misa-0.0.2.dist-info/RECORD
