Metadata-Version: 2.1
Name: django-misa
Version: 0.0.2
Summary: ISA organisation for metabolomic studies with Django
Home-page: https://mogi.readthedocs.io
Author: Thomas N lawson
Author-email: thomas.nigel.lawson@gmail.com
License: GPLv3
Platform: UNKNOWN
Classifier: Environment :: Web Environment
Classifier: Framework :: Django
Classifier: Framework :: Django :: 1.11
Classifier: Intended Audience :: Developers
Classifier: License :: OSI Approved :: GNU General Public License v3 (GPLv3)
Classifier: Operating System :: OS Independent
Classifier: Programming Language :: Python
Classifier: Programming Language :: Python :: 2.7
Classifier: Programming Language :: Python :: 3.6
Classifier: Topic :: Internet :: WWW/HTTP
Classifier: Topic :: Internet :: WWW/HTTP :: Dynamic Content
Requires-Dist: django (>=1.11.15)
Requires-Dist: django-gfiles
Requires-Dist: isatools
Requires-Dist: django-mbrowse
